setup.py
WarpedLMM.egg-info/PKG-INFO
WarpedLMM.egg-info/SOURCES.txt
WarpedLMM.egg-info/dependency_links.txt
WarpedLMM.egg-info/requires-FUSI1.txt
WarpedLMM.egg-info/requires.txt
WarpedLMM.egg-info/top_level.txt
warpedlmm/__init__.py
warpedlmm/__main__.py
warpedlmm/fastlmm_interface.py
warpedlmm/stepwise.py
warpedlmm/warpedlmm.py
warpedlmm/testing/__init__.py
warpedlmm/testing/tests.py
warpedlmm/util/__init__.py
warpedlmm/util/linalg.py
warpedlmm/util/qvalue.py
warpedlmm/util/transformations.py
warpedlmm/util/util.py
warpedlmm/util/warping_functions.py