Metadata-Version: 1.1
Name: WarpedLMM
Version: 0.21
Summary: Warped linear mixed model
Home-page: UNKNOWN
Author: Nicolo Fusi
Author-email: fusi@microsoft.com
License: Apache 2.0
Keywords: genetics GWAS
Platform: UNKNOWN
Classifier: License :: OSI Approved :: Apache Software License
